cuda_zarr/__init__.py
cuda_zarr/codecs.py
cuda_zarr/store.py
cuda_zarr-0.1.3.dist-info/METADATA
cuda_zarr-0.1.3.dist-info/WHEEL
cuda_zarr-0.1.3.dist-info/licenses/LICENSE
cuda_zarr-0.1.3.dist-info/RECORD
