Metadata-Version: 2.4
Name: cuda-zarr
Version: 0.1.3
Summary: A Zarr store and codecs for cuda.
Project-URL: Documentation, https://cuda-zarr.readthedocs.io/
Project-URL: Homepage, https://github.com/ilan-gold/cuda-zarr
Project-URL: Source, https://github.com/ilan-gold/cuda-zarr
Author: Ilan Gold
Maintainer-email: Ilan Gold <ilan.gold@helmholtz-munich.de>
License: Mozilla Public License Version 2.0
License-File: LICENSE
Classifier: Programming Language :: Python :: 3 :: Only
Classifier: Programming Language :: Python :: 3.10
Classifier: Programming Language :: Python :: 3.11
Classifier: Programming Language :: Python :: 3.12
Classifier: Programming Language :: Python :: 3.13
Requires-Python: >=3.10
Requires-Dist: zarr
Provides-Extra: cuda12
Requires-Dist: cupy-cuda12x; extra == 'cuda12'
Requires-Dist: kvikio-cu12; extra == 'cuda12'
Provides-Extra: dev
Requires-Dist: pre-commit; extra == 'dev'
Requires-Dist: twine>=4.0.2; extra == 'dev'
Provides-Extra: doc
Requires-Dist: myst-parser; extra == 'doc'
Requires-Dist: sphinx>=7.4.6; extra == 'doc'
Provides-Extra: test
Requires-Dist: aiohttp; extra == 'test'
Requires-Dist: coverage; extra == 'test'
Requires-Dist: pytest; extra == 'test'
Requires-Dist: pytest-asyncio; extra == 'test'
Requires-Dist: rangehttpserver; extra == 'test'
Requires-Dist: requests; extra == 'test'
Requires-Dist: zarr[test]; extra == 'test'
